summer_boot/__init__.py
summer_boot/cli.py
summer_boot/summer_boot.py
summer_boot-0.1.0.dist-info/AUTHORS.rst
summer_boot-0.1.0.dist-info/LICENSE
summer_boot-0.1.0.dist-info/METADATA
summer_boot-0.1.0.dist-info/WHEEL
summer_boot-0.1.0.dist-info/entry_points.txt
summer_boot-0.1.0.dist-info/top_level.txt
summer_boot-0.1.0.dist-info/RECORD
