Metadata-Version: 2.1
Name: summer-boot
Version: 0.1.0
Summary: Summer boot makes python simple, modern, productive and cloud-read to go.
Home-page: https://github.com/wuqunfei/summer_boot
Author: Qunfei Wu
Author-email: wu.qunfei@gmail.com
License: Apache Software License 2.0
Keywords: summer_boot
Platform: UNKNOWN
Classifier: Development Status :: 2 - Pre-Alpha
Classifier: Intended Audience :: Developers
Classifier: License :: OSI Approved :: Apache Software License
Classifier: Natural Language :: English
Classifier: Programming Language :: Python :: 3
Classifier: Programming Language :: Python :: 3.6
Classifier: Programming Language :: Python :: 3.7
Classifier: Programming Language :: Python :: 3.8
Classifier: Programming Language :: Python :: 3.9
Requires-Python: >=3.6
Requires-Dist: Click (>=7.0)
